timefeatures/widgets/__init__.py
timefeatures/widgets/owsavetodb.py
timefeatures/widgets/owtimefeaturesconstructor.py
timefeatures/widgets/owvardependencygraph.py
timefeatures/widgets/icons/graphgenerator.svg
timefeatures/widgets/icons/savedatadb.svg
timefeatures/widgets/icons/timefeature-xs.svg
timefeatures/widgets/icons/timefeature.svg
TimeFeatures-1.0.17.dist-info/LICENSE
TimeFeatures-1.0.17.dist-info/METADATA
TimeFeatures-1.0.17.dist-info/WHEEL
TimeFeatures-1.0.17.dist-info/entry_points.txt
TimeFeatures-1.0.17.dist-info/top_level.txt
TimeFeatures-1.0.17.dist-info/RECORD
