Metadata-Version: 2.1
Name: TimeFeatures
Version: 1.0.17
Summary: Timefeatures add-on for Orange 3 data mining software.
Home-page: https://github.com/alervgr/Orange-TimeFeatures
Author: Alejandro Rivas García
Author-email: alejandrorivasgarcia@gmail.com
License: GPL3+
Keywords: orange3 add-on,timefeatures,graph,time series,data mining,graph visualization,orange,addon,synthetic data
Classifier: Development Status :: 4 - Beta
Classifier: Environment :: Plugins
Classifier: Programming Language :: Python
Classifier: License :: OSI Approved :: GNU General Public License v3 or later (GPLv3+)
Classifier: Operating System :: OS Independent
Classifier: Topic :: Software Development :: Libraries :: Python Modules
Classifier: Intended Audience :: Education
Classifier: Intended Audience :: Science/Research
Classifier: Intended Audience :: Developers
License-File: LICENSE
